neurozen/__init__.py
neurozen-0.1.0.dist-info/METADATA
neurozen-0.1.0.dist-info/WHEEL
neurozen-0.1.0.dist-info/top_level.txt
neurozen-0.1.0.dist-info/RECORD
