Metadata-Version: 2.4
Name: neurozen
Version: 0.1.0
Summary: A modular agent framework
Author-email: Deepanshu Sharma <deepanshusharmx@gmail.com>
Classifier: Programming Language :: Python :: 3
Classifier: Operating System :: OS Independent
Requires-Python: >=3.8
